shapeGMMTorch/__init__.py
shapeGMMTorch/align.py
shapeGMMTorch/align_in_place.py
shapeGMMTorch/core.py
shapeGMMTorch/generation.py
shapeGMMTorch/version.py
shapeGMMTorch/.ipynb_checkpoints/align_in_place-checkpoint.py
shapeGMMTorch/em/__init__.py
shapeGMMTorch/em/kronecker.py
shapeGMMTorch/em/uniform.py
shapeGMMTorch/utils/__init__.py
shapeGMMTorch/utils/io.py
shapeGMMTorch/utils/plotting.py
shapeGMMTorch/utils/similarity.py
shapegmmtorch-2.1.0.dist-info/licenses/LICENSE
shapegmmtorch-2.1.0.dist-info/METADATA
shapegmmtorch-2.1.0.dist-info/WHEEL
shapegmmtorch-2.1.0.dist-info/top_level.txt
shapegmmtorch-2.1.0.dist-info/RECORD
