Metadata-Version: 2.4
Name: shapeGMMTorch
Version: 2.1.0
Summary: Gaussian Mixture Model clustering in size-and-shape space using PyTorch
Home-page: https://github.com/mccullaghlab/shapeGMMTorch
Author: Martin McCullagh
Author-email: Martin McCullagh <martin.mccullagh@okstate.edu>
License: MIT
Project-URL: Homepage, https://github.com/mccullaghlab/shapeGMMTorch
Project-URL: Repository, https://github.com/mccullaghlab/shapeGMMTorch
Project-URL: Issues, https://github.com/mccullaghlab/shapeGMMTorch/issues
Requires-Python: >=3.9
License-File: LICENSE
Requires-Dist: numpy
Requires-Dist: scipy
Requires-Dist: torch>=2.2
Requires-Dist: MDAnalysis
Requires-Dist: matplotlib
Provides-Extra: dev
Requires-Dist: pytest; extra == "dev"
Dynamic: author
Dynamic: home-page
Dynamic: license-file
Dynamic: requires-python
